idtrackerai_app/__init__.py
idtrackerai_app/__main__.py
idtrackerai_app/base_idtrackerai.py
idtrackerai_app/win_idtrackerai.py
idtrackerai_app/cli/__init__.py
idtrackerai_app/cli/__main__.py
idtrackerai_app/cli/ts/__init__.py
idtrackerai_app/cli/ts/ts.py
idtrackerai_app/cli/ts/utils.py
idtrackerai_app/gui/__init__.py
idtrackerai_app/gui/grapharea_win.py
idtrackerai_app/gui/player_win_interactions.py
idtrackerai_app/gui/range_win.py
idtrackerai_app/gui/roi_selection.py
idtrackerai_app/gui/setup_points_selection.py
pyforms-gui/__init__.py
pyforms-gui/setup.py
pyforms-gui/pyforms/__init__.py
pyforms-gui/pyforms/basewidget.py
pyforms-gui/pyforms/controls.py
pyforms-gui/pyforms/dialogs.py
pyforms-gui/pyforms/settings.py
pyforms-gui/pyforms_gui/__init__.py
pyforms-gui/pyforms_gui/allcontrols.py
pyforms-gui/pyforms_gui/appmanager.py
pyforms-gui/pyforms_gui/basewidget.py
pyforms-gui/pyforms_gui/organizers.py
pyforms-gui/pyforms_gui/resources_settings.py
pyforms-gui/pyforms_gui/settings.py
pyforms-gui/pyforms_gui/controls/__init__.py
pyforms-gui/pyforms_gui/controls/control_base.py
pyforms-gui/pyforms_gui/controls/control_boundingslider.py
pyforms-gui/pyforms_gui/controls/control_button.py
pyforms-gui/pyforms_gui/controls/control_checkbox.py
pyforms-gui/pyforms_gui/controls/control_checkboxlist.py
pyforms-gui/pyforms_gui/controls/control_codeeditor.py
pyforms-gui/pyforms_gui/controls/control_combo.py
pyforms-gui/pyforms_gui/controls/control_dir.py
pyforms-gui/pyforms_gui/controls/control_dockwidget.py
pyforms-gui/pyforms_gui/controls/control_emptywidget.py
pyforms-gui/pyforms_gui/controls/control_file.py
pyforms-gui/pyforms_gui/controls/control_filestree.py
pyforms-gui/pyforms_gui/controls/control_image.py
pyforms-gui/pyforms_gui/controls/control_label.py
pyforms-gui/pyforms_gui/controls/control_list.py
pyforms-gui/pyforms_gui/controls/control_matplotlib.py
pyforms-gui/pyforms_gui/controls/control_mdiarea.py
pyforms-gui/pyforms_gui/controls/control_number.py
idtrackerai_app_shaliulab-1.0.10.dist-info/METADATA
idtrackerai_app_shaliulab-1.0.10.dist-info/WHEEL
idtrackerai_app_shaliulab-1.0.10.dist-info/entry_points.txt
idtrackerai_app_shaliulab-1.0.10.dist-info/top_level.txt
idtrackerai_app_shaliulab-1.0.10.dist-info/RECORD
